datasette_mailto_links/__init__.py
datasette_mailto_links-0.3.1.dist-info/METADATA
datasette_mailto_links-0.3.1.dist-info/WHEEL
datasette_mailto_links-0.3.1.dist-info/entry_points.txt
datasette_mailto_links-0.3.1.dist-info/licenses/LICENSE
datasette_mailto_links-0.3.1.dist-info/RECORD
