Metadata-Version: 2.4
Name: datasette-mailto-links
Version: 0.3.1
Summary: Datasette plugin to render email addresses as mailto: links
License-Expression: MIT
License-File: LICENSE
Author: chris48s
Requires-Python: >=3.10
Classifier: Framework :: Datasette
Requires-Dist: datasette (>0)
Project-URL: Home, https://github.com/chris48s/datasette-mailto-links
Project-URL: Source, https://github.com/chris48s/datasette-mailto-links
